control_unit.sv
module control_unit(
    input logic [3:0] opcode,

    output logic RegWrite, ALUSrc, Branch,
    output logic [1:0] ALUControl
);


always_comb begin

    case (opcode)
        4'b0000: begin // and
            RegWrite = 1;
            ALUSrc = 0;
            ALUControl = 2'b00;
            Branch = 0;
        end
        4'b0001: begin // or
            RegWrite = 1;
            ALUSrc = 0;
            ALUControl = 2'b01;
            Branch = 0;
        end
        4'b0010: begin // add
            RegWrite = 1;
            ALUSrc = 0;
            ALUControl = 2'b10;
            Branch = 0;
        end
        4'b0011: begin // sub
            RegWrite = 1;
            ALUSrc = 0;
            ALUControl = 2'b11;
            Branch = 0;
        end
        4'b0100: begin // andi
            RegWrite = 1;
            ALUSrc = 1;
            ALUControl = 2'b00;
            Branch = 0;
        end
        4'b0101: begin // ori
            RegWrite = 1;
            ALUSrc = 1;
            ALUControl = 2'b01;
            Branch = 0;
        end
        4'b0110: begin // addi
            RegWrite = 1;
            ALUSrc = 1;
            ALUControl = 2'b10;
            Branch = 0;
        end
        4'b0111: begin // beq
            RegWrite = 0;
            ALUSrc = 0;
            ALUControl = 2'b11;
            Branch = 1;
        end
        default: begin
            RegWrite = 0;
            ALUSrc = 0;
            ALUControl = 2'b00;
            Branch = 0;
        end
    endcase
end

endmodule

control_unit_tb.sv
`timescale 1ns/1ps
`include "control_unit.sv"


module control_unit_tb;

    logic [3:0] opcode;

    logic RegWrite, ALUSrc, Branch;
    logic [1:0] ALUControl;

    control_unit uut (

         .opcode(opcode),

        .RegWrite(RegWrite),
        .ALUSrc(ALUSrc),

        .Branch(Branch),
        .ALUControl(ALUControl)
    );

    initial begin
        $dumpfile("control_unit_tb.vcd");
        $dumpvars(0, control_unit_tb);

        opcode = 4'b0000;

        for (int i = 0; i < 8; i++) begin
            opcode = i;

            #10;
        end

        $finish;
    end

    initial begin
        $monitor("opcode = %b, RegWrite = %b,  ALUSrc = %b, ALUControl = %b, Branch = %b", opcode, RegWrite, ALUSrc, ALUControl, Branch);
    end

endmodule

control_unit_tb.vcd
$date
	Sun Feb 23 22:16:00 2025
$end
$version
	Icarus Verilog
$end
$timescale
	1ps
$end
$scope module control_unit_tb $end
$var wire 1 ! RegWrite $end
$var wire 1 " Branch $end
$var wire 1 # ALUSrc $end
$var wire 2 $ ALUControl [1:0] $end
$var reg 4 % opcode [3:0] $end
$scope module uut $end
$var wire 4 & opcode [3:0] $end
$var reg 2 ' ALUControl [1:0] $end
$var reg 1 # ALUSrc $end
$var reg 1 " Branch $end
$var reg 1 ! RegWrite $end
$upscope $end
$scope begin $ivl_for_loop0 $end
$var integer 32 ( i [31:0] $end
$upscope $end
$upscope $end
$enddefinitions $end
$comment Show the parameter values. $end
$dumpall
$end
#0
$dumpvars
b0 (
b0 '
b0 &
b0 %
b0 $
0#
0"
1!
$end
#10000
b1 $
b1 '
1!
b1 %
b1 &
b1 (
#20000
b10 $
b10 '
1!
b10 %
b10 &
b10 (
#30000
b11 $
b11 '
1!
b11 %
b11 &
b11 (
#40000
1#
b0 $
b0 '
1!
b100 %
b100 &
b100 (
#50000
b1 $
b1 '
1#
1!
b101 %
b101 &
b101 (
#60000
b10 $
b10 '
1#
1!
b110 %
b110 &
b110 (
#70000
1"
b11 $
b11 '
0#
0!
b111 %
b111 &
b111 (
#80000
b1000 (
