alu.sv
module alu (
    output logic [7:0] ALUResult,
    output logic Zero,
    input logic [7:0] SrcA, SrcB,
    input logic [1:0] ALUControl
);

always_comb begin
    case (ALUControl)
        2'b00: ALUResult = SrcA & SrcB; 
        2'b01: ALUResult = SrcA | SrcB;  
        2'b10: ALUResult = SrcA + SrcB; 
        2'b11: ALUResult = SrcA - SrcB; 
        default: ALUResult = 8'b0;       
    endcase
    
    Zero = (ALUResult == 8'b0) ? 1'b1 : 1'b0;
end

endmodule

reg_file.sv
module reg_file (
    output logic [7:0] RD1, RD2, cpu_out,
    input  logic [3:0] RA1, RA2, WA,
    input  logic [7:0] ALUResult,
    input  logic write_enable, CLK
);


    logic [7:0] data[0:15];

    assign RD1 = data[RA1];
    assign RD2 = data[RA2];


    always_ff @(posedge CLK) begin
        if (write_enable && WA != 4'd0)
            data[WA] <= ALUResult;
    end

    assign cpu_out = data[15];

    initial begin
        for (int i = 0; i < 16; i++)
            data[i] = 8'd0;
    end

endmodule

reg_file_alu.sv
`include "alu.sv"
`include "reg_file.sv"





module reg_file_alu (
    output logic [7:0] ALUResult, cpu_out,
    output logic Zero,
    input logic [3:0] RA1, RA2, WA,
    input logic [7:0] immediate,
    input logic write_enable, ALUsrc, CLK,
    input logic [1:0] ALUControl
);

logic [7:0] RD1, RD2, SrcA, SrcB;

assign SrcA = RD1;

reg_file u_reg_file (
    RD1,RD2, cpu_out,RA1,RA2, WA, ALUResult, write_enable, CLK
);

alu u_alu (
    ALUResult, Zero, SrcA, SrcB, ALUControl
);

always_comb begin
    case(ALUsrc)
    1'b0: SrcB = RD2;
    1'b1: SrcB = immediate;
endcase
end


endmodule

control_unit.sv
module control_unit(
    input logic [3:0] opcode,

    output logic RegWrite, ALUSrc, Branch,
    output logic [1:0] ALUControl
);


always_comb begin

    case (opcode)
        4'b0000: begin // and
            RegWrite = 1;
            ALUSrc = 0;
            ALUControl = 2'b00;
            Branch = 0;
        end
        4'b0001: begin // or
            RegWrite = 1;
            ALUSrc = 0;
            ALUControl = 2'b01;
            Branch = 0;
        end
        4'b0010: begin // add
            RegWrite = 1;
            ALUSrc = 0;
            ALUControl = 2'b10;
            Branch = 0;
        end
        4'b0011: begin // sub
            RegWrite = 1;
            ALUSrc = 0;
            ALUControl = 2'b11;
            Branch = 0;
        end
        4'b0100: begin // andi
            RegWrite = 1;
            ALUSrc = 1;
            ALUControl = 2'b00;
            Branch = 0;
        end
        4'b0101: begin // ori
            RegWrite = 1;
            ALUSrc = 1;
            ALUControl = 2'b01;
            Branch = 0;
        end
        4'b0110: begin // addi
            RegWrite = 1;
            ALUSrc = 1;
            ALUControl = 2'b10;
            Branch = 0;
        end
        4'b0111: begin // beq
            RegWrite = 0;
            ALUSrc = 0;
            ALUControl = 2'b11;
            Branch = 1;
        end
        default: begin
            RegWrite = 0;
            ALUSrc = 0;
            ALUControl = 2'b00;
            Branch = 0;
        end
    endcase
end

endmodule

instruction_memory.sv
module instruction_memory(
    output logic [23:0] Instr,
    input logic [7:0] PC
);

logic [23:0] data_ROM [0:255];

initial begin
    $readmemh("program.txt", data_ROM);
end

assign Instr = data_ROM[PC];

endmodule

pc.sv
module PC(
    input logic CLK, reset, PCsrc,
    input logic [7:0] immediate,
    output logic [7:0] PC
);

always_ff @ (posedge CLK or posedge reset) begin
    if (reset)
        PC <= 8'b0;
    else if (PCsrc)
        PC <= immediate;
    else
        PC <= PC + 1;
end

endmodule

instruction_memory_pc.sv
`include "pc.sv"
`include "instruction_memory.sv"


module instruction_memory_pc (
    output logic [23:0] Instr,

    input logic CLK, reset, PCsrc,
    input logic [7:0] immediate

);

logic [7:0] PC;

PC u_pc (
    .CLK(CLK),

    .reset(reset),
    .PCsrc(PCsrc),
    .immediate(immediate),
    .PC(PC)
);

instruction_memory u_instruction_memory (

    .Instr(Instr),
    .PC(PC)
);

endmodule

cpu.sv
`include "instruction_memory_pc.sv"
`include "control_unit.sv"
`include "reg_file_alu.sv"
module cpu(
    output logic [7:0] ALUResult, cpu_out,

    input logic CLK, reset
);
//Creating the reg_file_alu
logic Zero;
logic [3:0] RA1, RA2, WA;
logic [7:0] immediate;
logic write_enable;
logic ALUSrc_1, ALUSrc_2;
logic [1:0] ALUControl;
//Creating the control_unit
logic [3:0] opcode;
logic RegWrite, Branch;
//Creating the instruction_memory_pc
logic [23:0] Instr;
logic PCsrc;
//logic [7:0] immediate;
instruction_memory_pc u_instruction_memory_pc (
    .Instr(Instr),
    .CLK(CLK),
    .reset(reset),
    .PCsrc(PCsrc),
    .immediate(immediate)
);
control_unit u_control_unit (
    .opcode(opcode),
    .RegWrite(RegWrite),
    .ALUSrc(ALUSrc_1),
    .Branch(Branch),
    .ALUControl(ALUControl)
);
assign ALUSrc_2 = ALUSrc_1;
reg_file_alu u_reg_file_alu (
    .ALUResult(ALUResult),
    .cpu_out(cpu_out),
    .Zero(Zero),
    .RA1(RA1),
    .RA2(RA2),
    .WA(WA),
    .immediate(immediate),
    .write_enable(write_enable),
    .ALUsrc(ALUSrc_2),
    .CLK(CLK),
    .ALUControl(ALUControl)
);
//wires connecting the Reg_file_alu
assign write_enable = RegWrite;
assign RA1 = Instr[15:12];
assign RA2 = Instr[11:8];
assign WA = Instr[19:16];
assign immediate = Instr[7:0];
//wires connecting the control_unit
assign opcode = Instr[23:20];
//wires connecting the instruction_memory_pc
assign PCsrc = Branch & Zero;
endmodule

cpu_tb.sv
`timescale 1ns/1ps
`include "cpu.sv"

module cpu_tb;

    logic CLK, reset;
    logic [7:0] ALUResult, cpu_out;

    cpu uut (
        .CLK(CLK),
        .reset(reset),
        .ALUResult(ALUResult),
        .cpu_out(cpu_out)
    );
    initial begin
        CLK = 0;
        forever #5 CLK = ~CLK;
    end

    initial begin
        $dumpfile("cpu_tb.vcd");
        $dumpvars(0, cpu_tb);

        reset = 1;

        #10 reset = 0;

        for (int i = 0; i < 32; i++) begin
            #10;
        end

        $finish;
    end

    initial begin
        $monitor("At time %t, ALUResult = %h, cpu_out = %h", $time, ALUResult, cpu_out);
    end

endmodule

cpu_tb.vcd
$date
	Mon Feb 24 01:56:00 2025
$end
$version
	Icarus Verilog
$end
$timescale
	1ps
$end
$scope module cpu_tb $end
$var wire 8 ! cpu_out [7:0] $end
$var wire 8 " ALUResult [7:0] $end
$var reg 1 # CLK $end
$var reg 1 $ reset $end
$scope module uut $end
$var wire 1 % ALUSrc_2 $end
$var wire 1 # CLK $end
$var wire 1 & PCsrc $end
$var wire 1 $ reset $end
$var wire 1 ' write_enable $end
$var wire 4 ( opcode [3:0] $end
$var wire 8 ) immediate [7:0] $end
$var wire 8 * cpu_out [7:0] $end
$var wire 1 + Zero $end
$var wire 4 , WA [3:0] $end
$var wire 1 - RegWrite $end
$var wire 4 . RA2 [3:0] $end
$var wire 4 / RA1 [3:0] $end
$var wire 24 0 Instr [23:0] $end
$var wire 1 1 Branch $end
$var wire 1 2 ALUSrc_1 $end
$var wire 8 3 ALUResult [7:0] $end
$var wire 2 4 ALUControl [1:0] $end
$scope module u_control_unit $end
$var wire 4 5 opcode [3:0] $end
$var reg 2 6 ALUControl [1:0] $end
$var reg 1 2 ALUSrc $end
$var reg 1 1 Branch $end
$var reg 1 - RegWrite $end
$upscope $end
$scope module u_instruction_memory_pc $end
$var wire 1 # CLK $end
$var wire 1 & PCsrc $end
$var wire 8 7 immediate [7:0] $end
$var wire 1 $ reset $end
$var wire 8 8 PC [7:0] $end
$var wire 24 9 Instr [23:0] $end
$scope module u_instruction_memory $end
$var wire 24 : Instr [23:0] $end
$var wire 8 ; PC [7:0] $end
$upscope $end
$scope module u_pc $end
$var wire 1 # CLK $end
$var wire 1 & PCsrc $end
$var wire 8 < immediate [7:0] $end
$var wire 1 $ reset $end
$var reg 8 = PC [7:0] $end
$upscope $end
$upscope $end
$scope module u_reg_file_alu $end
$var wire 2 > ALUControl [1:0] $end
$var wire 1 % ALUsrc $end
$var wire 1 # CLK $end
$var wire 4 ? RA1 [3:0] $end
$var wire 4 @ RA2 [3:0] $end
$var wire 8 A SrcA [7:0] $end
$var wire 4 B WA [3:0] $end
$var wire 8 C immediate [7:0] $end
$var wire 1 ' write_enable $end
$var wire 8 D cpu_out [7:0] $end
$var wire 1 + Zero $end
$var wire 8 E RD2 [7:0] $end
$var wire 8 F RD1 [7:0] $end
$var wire 8 G ALUResult [7:0] $end
$var reg 8 H SrcB [7:0] $end
$scope module u_alu $end
$var wire 2 I ALUControl [1:0] $end
$var wire 8 J SrcA [7:0] $end
$var wire 8 K SrcB [7:0] $end
$var reg 8 L ALUResult [7:0] $end
$var reg 1 + Zero $end
$upscope $end
$scope module u_reg_file $end
$var wire 8 M ALUResult [7:0] $end
$var wire 1 # CLK $end
$var wire 4 N RA1 [3:0] $end
$var wire 4 O RA2 [3:0] $end
$var wire 8 P RD1 [7:0] $end
$var wire 8 Q RD2 [7:0] $end
$var wire 4 R WA [3:0] $end
$var wire 8 S cpu_out [7:0] $end
$var wire 1 ' write_enable $end
$scope begin $ivl_for_loop0 $end
$var integer 32 T i [31:0] $end
$upscope $end
$upscope $end
$upscope $end
$upscope $end
$scope begin $ivl_for_loop1 $end
$var integer 32 U i [31:0] $end
$upscope $end
$upscope $end
$enddefinitions $end
$comment Show the parameter values. $end
$dumpall
$end
#0
$dumpvars
b0 U
b10000 T
b0 S
b1 R
b0 Q
b0 P
b0 O
b0 N
b1 M
b1 L
b1 K
b0 J
b10 I
b1 H
b1 G
b0 F
b0 E
b0 D
b1 C
b1 B
b0 A
b0 @
b0 ?
b10 >
b0 =
b1 <
b0 ;
b11000010000000000000001 :
b11000010000000000000001 9
b0 8
b1 7
b10 6
b110 5
b10 4
b1 3
12
01
b11000010000000000000001 0
b0 /
b0 .
1-
b1 ,
0+
b0 *
b1 )
b110 (
1'
0&
1%
1$
0#
b1 "
b0 !
$end
#5000
1#
#10000
0#
0$
#15000
b100000 "
b100000 3
b100000 G
b100000 L
b100000 M
b100000 H
b100000 K
b100000 )
b100000 7
b100000 <
b100000 C
b10 ,
b10 B
b10 R
b11000100000000000100000 0
b11000100000000000100000 9
b11000100000000000100000 :
b1 8
b1 ;
b1 =
1#
#20000
0#
b1 U
#25000
1+
b0 "
b0 3
b0 G
b0 L
b0 M
b0 H
b0 K
b0 )
b0 7
b0 <
b0 C
b1111 ,
b1111 B
b1111 R
b11011110000000000000000 0
b11011110000000000000000 9
b11011110000000000000000 :
b10 8
b10 ;
b10 =
1#
#30000
0#
b10 U
#35000
11
b11 4
b11 6
b11 >
b11 I
0%
02
0'
0-
b100000 H
b100000 K
0+
b11100001 "
b11100001 3
b11100001 G
b11100001 L
b11100001 M
b111 (
b111 5
b111 )
b111 7
b111 <
b111 C
b0 ,
b0 B
b0 R
b100000 E
b100000 Q
b10 .
b10 @
b10 O
b1 A
b1 J
b1 F
b1 P
b1 /
b1 ?
b1 N
b11100000001001000000111 0
b11100000001001000000111 9
b11100000001001000000111 :
b11 8
b11 ;
b11 =
1#
#40000
0#
b11 U
#45000
b10 "
b10 3
b10 G
b10 L
b10 M
01
b10 4
b10 6
b10 >
b10 I
1'
1-
b1 H
b1 K
b10 (
b10 5
b0 )
b0 7
b0 <
b0 C
b1 ,
b1 B
b1 R
b1 E
b1 Q
b1 .
b1 @
b1 O
b1000010001000100000000 0
b1000010001000100000000 9
b1000010001000100000000 :
b100 8
b100 ;
b100 =
1#
#50000
0#
b100 U
#55000
0+
1%
12
b110 (
b110 5
b1 )
b1 7
b1 <
b1 C
b1111 ,
b1111 B
b1111 R
b0 .
b0 @
b0 O
b1111 /
b1111 ?
b1111 N
b1 "
b1 3
b1 G
b1 L
b1 M
b1 H
b1 K
b11011111111000000000001 0
b11011111111000000000001 9
b11011111111000000000001 :
b101 8
b101 ;
b101 =
b0 A
b0 J
b0 F
b0 P
b0 E
b0 Q
1#
#60000
0#
b101 U
#65000
1&
1+
11
b11 4
b11 6
b11 >
b11 I
0%
02
0'
0-
b0 H
b0 K
b111 (
b111 5
b11 )
b11 7
b11 <
b11 C
b0 ,
b0 B
b0 R
b0 /
b0 ?
b0 N
b0 "
b0 3
b0 G
b0 L
b0 M
b11100000000000000000011 0
b11100000000000000000011 9
b11100000000000000000011 :
b110 8
b110 ;
b110 =
b0 A
b0 J
b0 F
b0 P
b1 !
b1 *
b1 D
b1 S
1#
#70000
0#
b110 U
#75000
0&
b100000 H
b100000 K
0+
b11100010 "
b11100010 3
b11100010 G
b11100010 L
b11100010 M
b111 )
b111 7
b111 <
b111 C
b100000 E
b100000 Q
b10 .
b10 @
b10 O
b10 A
b10 J
b10 F
b10 P
b1 /
b1 ?
b1 N
b11100000001001000000111 0
b11100000001001000000111 9
b11100000001001000000111 :
b11 8
b11 ;
b11 =
1#
#80000
0#
b111 U
#85000
b100 "
b100 3
b100 G
b100 L
b100 M
01
b10 4
b10 6
b10 >
b10 I
1'
1-
b10 H
b10 K
b10 (
b10 5
b0 )
b0 7
b0 <
b0 C
b1 ,
b1 B
b1 R
b10 E
b10 Q
b1 .
b1 @
b1 O
b1000010001000100000000 0
b1000010001000100000000 9
b1000010001000100000000 :
b100 8
b100 ;
b100 =
1#
#90000
0#
b1000 U
#95000
1%
12
b110 (
b110 5
b1 )
b1 7
b1 <
b1 C
b1111 ,
b1111 B
b1111 R
b0 .
b0 @
b0 O
b1111 /
b1111 ?
b1111 N
b10 "
b10 3
b10 G
b10 L
b10 M
b1 H
b1 K
b11011111111000000000001 0
b11011111111000000000001 9
b11011111111000000000001 :
b101 8
b101 ;
b101 =
b1 A
b1 J
b1 F
b1 P
b0 E
b0 Q
1#
#100000
0#
b1001 U
#105000
1&
1+
11
b11 4
b11 6
b11 >
b11 I
0%
02
0'
0-
b0 H
b0 K
b111 (
b111 5
b11 )
b11 7
b11 <
b11 C
b0 ,
b0 B
b0 R
b0 /
b0 ?
b0 N
b0 "
b0 3
b0 G
b0 L
b0 M
b11100000000000000000011 0
b11100000000000000000011 9
b11100000000000000000011 :
b110 8
b110 ;
b110 =
b0 A
b0 J
b0 F
b0 P
b10 !
b10 *
b10 D
b10 S
1#
#110000
0#
b1010 U
#115000
0&
b100000 H
b100000 K
0+
b11100100 "
b11100100 3
b11100100 G
b11100100 L
b11100100 M
b111 )
b111 7
b111 <
b111 C
b100000 E
b100000 Q
b10 .
b10 @
b10 O
b100 A
b100 J
b100 F
b100 P
b1 /
b1 ?
b1 N
b11100000001001000000111 0
b11100000001001000000111 9
b11100000001001000000111 :
b11 8
b11 ;
b11 =
1#
#120000
0#
b1011 U
#125000
b1000 "
b1000 3
b1000 G
b1000 L
b1000 M
01
b10 4
b10 6
b10 >
b10 I
1'
1-
b100 H
b100 K
b10 (
b10 5
b0 )
b0 7
b0 <
b0 C
b1 ,
b1 B
b1 R
b100 E
b100 Q
b1 .
b1 @
b1 O
b1000010001000100000000 0
b1000010001000100000000 9
b1000010001000100000000 :
b100 8
b100 ;
b100 =
1#
#130000
0#
b1100 U
#135000
1%
12
b110 (
b110 5
b1 )
b1 7
b1 <
b1 C
b1111 ,
b1111 B
b1111 R
b0 .
b0 @
b0 O
b1111 /
b1111 ?
b1111 N
b11 "
b11 3
b11 G
b11 L
b11 M
b1 H
b1 K
b11011111111000000000001 0
b11011111111000000000001 9
b11011111111000000000001 :
b101 8
b101 ;
b101 =
b10 A
b10 J
b10 F
b10 P
b0 E
b0 Q
1#
#140000
0#
b1101 U
#145000
1&
1+
11
b11 4
b11 6
b11 >
b11 I
0%
02
0'
0-
b0 H
b0 K
b111 (
b111 5
b11 )
b11 7
b11 <
b11 C
b0 ,
b0 B
b0 R
b0 /
b0 ?
b0 N
b0 "
b0 3
b0 G
b0 L
b0 M
b11100000000000000000011 0
b11100000000000000000011 9
b11100000000000000000011 :
b110 8
b110 ;
b110 =
b0 A
b0 J
b0 F
b0 P
b11 !
b11 *
b11 D
b11 S
1#
#150000
0#
b1110 U
#155000
0&
b100000 H
b100000 K
0+
b11101000 "
b11101000 3
b11101000 G
b11101000 L
b11101000 M
b111 )
b111 7
b111 <
b111 C
b100000 E
b100000 Q
b10 .
b10 @
b10 O
b1000 A
b1000 J
b1000 F
b1000 P
b1 /
b1 ?
b1 N
b11100000001001000000111 0
b11100000001001000000111 9
b11100000001001000000111 :
b11 8
b11 ;
b11 =
1#
#160000
0#
b1111 U
#165000
b10000 "
b10000 3
b10000 G
b10000 L
b10000 M
01
b10 4
b10 6
b10 >
b10 I
1'
1-
b1000 H
b1000 K
b10 (
b10 5
b0 )
b0 7
b0 <
b0 C
b1 ,
b1 B
b1 R
b1000 E
b1000 Q
b1 .
b1 @
b1 O
b1000010001000100000000 0
b1000010001000100000000 9
b1000010001000100000000 :
b100 8
b100 ;
b100 =
1#
#170000
0#
b10000 U
#175000
1%
12
b110 (
b110 5
b1 )
b1 7
b1 <
b1 C
b1111 ,
b1111 B
b1111 R
b0 .
b0 @
b0 O
b1111 /
b1111 ?
b1111 N
b100 "
b100 3
b100 G
b100 L
b100 M
b1 H
b1 K
b11011111111000000000001 0
b11011111111000000000001 9
b11011111111000000000001 :
b101 8
b101 ;
b101 =
b11 A
b11 J
b11 F
b11 P
b0 E
b0 Q
1#
#180000
0#
b10001 U
#185000
1&
1+
11
b11 4
b11 6
b11 >
b11 I
0%
02
0'
0-
b0 H
b0 K
b111 (
b111 5
b11 )
b11 7
b11 <
b11 C
b0 ,
b0 B
b0 R
b0 /
b0 ?
b0 N
b0 "
b0 3
b0 G
b0 L
b0 M
b11100000000000000000011 0
b11100000000000000000011 9
b11100000000000000000011 :
b110 8
b110 ;
b110 =
b0 A
b0 J
b0 F
b0 P
b100 !
b100 *
b100 D
b100 S
1#
#190000
0#
b10010 U
#195000
0&
b100000 H
b100000 K
0+
b11110000 "
b11110000 3
b11110000 G
b11110000 L
b11110000 M
b111 )
b111 7
b111 <
b111 C
b100000 E
b100000 Q
b10 .
b10 @
b10 O
b10000 A
b10000 J
b10000 F
b10000 P
b1 /
b1 ?
b1 N
b11100000001001000000111 0
b11100000001001000000111 9
b11100000001001000000111 :
b11 8
b11 ;
b11 =
1#
#200000
0#
b10011 U
#205000
b100000 "
b100000 3
b100000 G
b100000 L
b100000 M
01
b10 4
b10 6
b10 >
b10 I
1'
1-
b10000 H
b10000 K
b10 (
b10 5
b0 )
b0 7
b0 <
b0 C
b1 ,
b1 B
b1 R
b10000 E
b10000 Q
b1 .
b1 @
b1 O
b1000010001000100000000 0
b1000010001000100000000 9
b1000010001000100000000 :
b100 8
b100 ;
b100 =
1#
#210000
0#
b10100 U
#215000
1%
12
b110 (
b110 5
b1 )
b1 7
b1 <
b1 C
b1111 ,
b1111 B
b1111 R
b0 .
b0 @
b0 O
b1111 /
b1111 ?
b1111 N
b101 "
b101 3
b101 G
b101 L
b101 M
b1 H
b1 K
b11011111111000000000001 0
b11011111111000000000001 9
b11011111111000000000001 :
b101 8
b101 ;
b101 =
b100 A
b100 J
b100 F
b100 P
b0 E
b0 Q
1#
#220000
0#
b10101 U
#225000
1&
1+
11
b11 4
b11 6
b11 >
b11 I
0%
02
0'
0-
b0 H
b0 K
b111 (
b111 5
b11 )
b11 7
b11 <
b11 C
b0 ,
b0 B
b0 R
b0 /
b0 ?
b0 N
b0 "
b0 3
b0 G
b0 L
b0 M
b11100000000000000000011 0
b11100000000000000000011 9
b11100000000000000000011 :
b110 8
b110 ;
b110 =
b0 A
b0 J
b0 F
b0 P
b101 !
b101 *
b101 D
b101 S
1#
#230000
0#
b10110 U
#235000
1&
b100000 H
b100000 K
1+
b0 "
b0 3
b0 G
b0 L
b0 M
b111 )
b111 7
b111 <
b111 C
b100000 E
b100000 Q
b10 .
b10 @
b10 O
b100000 A
b100000 J
b100000 F
b100000 P
b1 /
b1 ?
b1 N
b11100000001001000000111 0
b11100000001001000000111 9
b11100000001001000000111 :
b11 8
b11 ;
b11 =
1#
#240000
0#
b10111 U
#245000
1&
b0 H
b0 K
1+
b0 "
b0 3
b0 G
b0 L
b0 M
b0 E
b0 Q
b0 .
b0 @
b0 O
b0 A
b0 J
b0 F
b0 P
b0 /
b0 ?
b0 N
b11100000000000000000111 0
b11100000000000000000111 9
b11100000000000000000111 :
b111 8
b111 ;
b111 =
1#
#250000
0#
b11000 U
#255000
1#
#260000
0#
b11001 U
#265000
1#
#270000
0#
b11010 U
#275000
1#
#280000
0#
b11011 U
#285000
1#
#290000
0#
b11100 U
#295000
1#
#300000
0#
b11101 U
#305000
1#
#310000
0#
b11110 U
#315000
1#
#320000
0#
b11111 U
#325000
1#
#330000
0#
b100000 U
#335000
1#
#340000
0#
b100001 U
#345000
1#
#350000
0#
b100010 U
#355000
1#
#360000
0#
b100011 U
#365000
1#
#370000
0#
b100100 U
#375000
1#
#380000
0#
b100101 U
#385000
1#
#390000
0#
b100110 U
#395000
1#
#400000
0#
b100111 U
#405000
1#
#410000
0#
b101000 U
#415000
1#
#420000
0#
b101001 U
#425000
1#
#430000
0#
b101010 U
#435000
1#
#440000
0#
b101011 U
#445000
1#
#450000
0#
b101100 U
#455000
1#
#460000
0#
b101101 U
#465000
1#
#470000
0#
b101110 U
#475000
1#
#480000
0#
b101111 U
#485000
1#
#490000
0#
b110000 U
#495000
1#
#500000
0#
b110001 U
#505000
1#
#510000
0#
b110010 U
#515000
1#
#520000
0#
b110011 U
#525000
1#
#530000
0#
b110100 U
#535000
1#
#540000
0#
b110101 U
#545000
1#
#550000
0#
b110110 U
#555000
1#
#560000
0#
b110111 U
#565000
1#
#570000
0#
b111000 U
#575000
1#
#580000
0#
b111001 U
#585000
1#
#590000
0#
b111010 U
#595000
1#
#600000
0#
b111011 U
#605000
1#
#610000
0#
b111100 U
#615000
1#
#620000
0#
b111101 U
#625000
1#
#630000
0#
b111110 U
#635000
1#
#640000
0#
b111111 U
#645000
1#
#650000
0#
b1000000 U
