instruction_memory.sv
module instruction_memory(
    output logic [23:0] Instr,
    input logic [7:0] PC
);

logic [23:0] data_ROM [0:255];

initial begin
    $readmemh("program.txt", data_ROM);
end

assign Instr = data_ROM[PC];

endmodule

instruction_memory_tb.sv
`timescale 1ns/1ps
`include "instruction_memory.sv"


module instruction_memory_tb;

    logic [7:0] PC;
    logic [23:0] Instr;

    instruction_memory uut (
        .Instr(Instr),
        .PC(PC)
    );

    initial begin
    $dumpfile("instruction_memory_tb.vcd");
    $dumpvars(0, instruction_memory_tb);
    end
    initial begin

        PC = 0;

        for (int i = 0; i < 8; i++) begin // running a full cycle
            #10;
            PC = i;
        end
        

        #10 $finish;
    end

    initial begin
        $monitor("PC = %h, Instr = %h", PC, Instr);
    end

endmodule

instruction_memory_tb.vcd
$date
	Mon Feb 24 02:13:49 2025
$end
$version
	Icarus Verilog
$end
$timescale
	1ps
$end
$scope module instruction_memory_tb $end
$var wire 24 ! Instr [23:0] $end
$var reg 8 " PC [7:0] $end
$scope module uut $end
$var wire 24 # Instr [23:0] $end
$var wire 8 $ PC [7:0] $end
$upscope $end
$scope begin $ivl_for_loop0 $end
$var integer 32 % i [31:0] $end
$upscope $end
$upscope $end
$enddefinitions $end
$comment Show the parameter values. $end
$dumpall
$end
#0
$dumpvars
b0 %
b0 $
b11000010000000000000001 #
b0 "
b11000010000000000000001 !
$end
#10000
b1 %
#20000
b10 %
b11000100000000000100000 !
b11000100000000000100000 #
b1 "
b1 $
#30000
b11 %
b11011110000000000000000 !
b11011110000000000000000 #
b10 "
b10 $
#40000
b100 %
b11100000001001000000111 !
b11100000001001000000111 #
b11 "
b11 $
#50000
b101 %
b1000010001000100000000 !
b1000010001000100000000 #
b100 "
b100 $
#60000
b110 %
b11011111111000000000001 !
b11011111111000000000001 #
b101 "
b101 $
#70000
b111 %
b11100000000000000000011 !
b11100000000000000000011 #
b110 "
b110 $
#80000
b1000 %
b11100000000000000000111 !
b11100000000000000000111 #
b111 "
b111 $
