instruction_memory.sv
module instruction_memory(
    output logic [23:0] Instr,
    input logic [7:0] PC
);

logic [23:0] data_ROM [0:255];

initial begin
    $readmemh("program.txt", data_ROM);
end

assign Instr = data_ROM[PC];

endmodule

pc.sv
module PC(
    input logic CLK, reset, PCsrc,
    input logic [7:0] immediate,
    output logic [7:0] PC
);

always_ff @ (posedge CLK or posedge reset) begin
    if (reset)
        PC <= 8'b0;
    else if (PCsrc)
        PC <= immediate;
    else
        PC <= PC + 1;
end

endmodule

instruction_memory_pc.sv
`include "pc.sv"
`include "instruction_memory.sv"


module instruction_memory_pc (
    output logic [23:0] Instr,

    input logic CLK, reset, PCsrc,
    input logic [7:0] immediate

);

logic [7:0] PC;

PC u_pc (
    .CLK(CLK),

    .reset(reset),
    .PCsrc(PCsrc),
    .immediate(immediate),
    .PC(PC)
);

instruction_memory u_instruction_memory (

    .Instr(Instr),
    .PC(PC)
);

endmodule

instruction_memory_pc_tb.sv
`timescale 1ns/1ps
`include "instruction_memory_pc.sv"

module instruction_memory_pc_tb;
    logic CLK, reset, PCsrc;
    logic [7:0] immediate;
    logic [23:0] Instr;


    instruction_memory_pc uut (
        .Instr(Instr),
        .CLK(CLK),
        .reset(reset),
        .PCsrc(PCsrc),
        .immediate(immediate)
    );
    // Clock generation
    initial begin
        CLK = 0;
        forever #5 CLK = ~CLK;
    end
    initial begin
        $dumpfile("instruction_memory_pc_tb.vcd");
        $dumpvars(0, instruction_memory_pc_tb);
        reset = 1;
        PCsrc = 0;
        immediate = 8'h00;
        #10 reset = 0;
        for (int i = 0; i < 8; i++) begin // running a full cycle
            #10;
        end
        

        for (int i = 0; i < 4; i++) begin // Testing immediates
        #10;
        PCsrc = 1;
        immediate = i*2;
        #10;
        end
        $finish;
    end


    initial begin
        $monitor("Instr = %h, reset = %b, PCsrc = %b, immediate = %d", Instr, reset, PCsrc, immediate); // did not display time since redundant
    end

endmodule

instruction_memory_pc_tb.vcd
$date
	Mon Feb 24 01:51:23 2025
$end
$version
	Icarus Verilog
$end
$timescale
	1ps
$end
$scope module instruction_memory_pc_tb $end
$var wire 24 ! Instr [23:0] $end
$var reg 1 " CLK $end
$var reg 1 # PCsrc $end
$var reg 8 $ immediate [7:0] $end
$var reg 1 % reset $end
$scope module uut $end
$var wire 1 " CLK $end
$var wire 1 # PCsrc $end
$var wire 8 & immediate [7:0] $end
$var wire 1 % reset $end
$var wire 8 ' PC [7:0] $end
$var wire 24 ( Instr [23:0] $end
$scope module u_instruction_memory $end
$var wire 24 ) Instr [23:0] $end
$var wire 8 * PC [7:0] $end
$upscope $end
$scope module u_pc $end
$var wire 1 " CLK $end
$var wire 1 # PCsrc $end
$var wire 8 + immediate [7:0] $end
$var wire 1 % reset $end
$var reg 8 , PC [7:0] $end
$upscope $end
$upscope $end
$scope begin $ivl_for_loop0 $end
$var integer 32 - i [31:0] $end
$upscope $end
$scope begin $ivl_for_loop1 $end
$var integer 32 . i [31:0] $end
$upscope $end
$upscope $end
$enddefinitions $end
$comment Show the parameter values. $end
$dumpall
$end
#0
$dumpvars
b0 .
b0 -
b0 ,
b0 +
b0 *
b11000010000000000000001 )
b11000010000000000000001 (
b0 '
b0 &
1%
b0 $
0#
0"
b11000010000000000000001 !
$end
#5000
1"
#10000
0"
0%
#15000
b11000100000000000100000 !
b11000100000000000100000 (
b11000100000000000100000 )
b1 '
b1 *
b1 ,
1"
#20000
0"
b1 -
#25000
b11011110000000000000000 !
b11011110000000000000000 (
b11011110000000000000000 )
b10 '
b10 *
b10 ,
1"
#30000
0"
b10 -
#35000
b11100000001001000000111 !
b11100000001001000000111 (
b11100000001001000000111 )
b11 '
b11 *
b11 ,
1"
#40000
0"
b11 -
#45000
b1000010001000100000000 !
b1000010001000100000000 (
b1000010001000100000000 )
b100 '
b100 *
b100 ,
1"
#50000
0"
b100 -
#55000
b11011111111000000000001 !
b11011111111000000000001 (
b11011111111000000000001 )
b101 '
b101 *
b101 ,
1"
#60000
0"
b101 -
#65000
b11100000000000000000011 !
b11100000000000000000011 (
b11100000000000000000011 )
b110 '
b110 *
b110 ,
1"
#70000
0"
b110 -
#75000
b11100000000000000000111 !
b11100000000000000000111 (
b11100000000000000000111 )
b111 '
b111 *
b111 ,
1"
#80000
0"
b111 -
#85000
bx !
bx (
bx )
b1000 '
b1000 *
b1000 ,
1"
#90000
0"
b1000 -
#95000
b1001 '
b1001 *
b1001 ,
1"
#100000
0"
1#
#105000
b11000010000000000000001 !
b11000010000000000000001 (
b11000010000000000000001 )
b0 '
b0 *
b0 ,
1"
#110000
0"
b1 .
#115000
1"
#120000
0"
b10 $
b10 &
b10 +
#125000
b11011110000000000000000 !
b11011110000000000000000 (
b11011110000000000000000 )
b10 '
b10 *
b10 ,
1"
#130000
0"
b10 .
#135000
1"
#140000
0"
b100 $
b100 &
b100 +
#145000
b1000010001000100000000 !
b1000010001000100000000 (
b1000010001000100000000 )
b100 '
b100 *
b100 ,
1"
#150000
0"
b11 .
#155000
1"
#160000
0"
b110 $
b110 &
b110 +
#165000
b11100000000000000000011 !
b11100000000000000000011 (
b11100000000000000000011 )
b110 '
b110 *
b110 ,
1"
#170000
0"
b100 .
