pc.sv
module PC(
    input logic CLK, reset, PCsrc,
    input logic [7:0] immediate,
    output logic [7:0] PC
);

always_ff @ (posedge CLK or posedge reset) begin
    if (reset)
        PC <= 8'b0;
    else if (PCsrc)
        PC <= immediate;
    else
        PC <= PC + 1;
end

endmodule

pc_tb.sv
`timescale 1ns/1ps
`include "pc.sv"

module pc_tb;
    logic CLK, reset, PCsrc;
    logic [7:0] immediate;

    logic [7:0] PC;

    PC uut (
        .CLK(CLK),
        .reset(reset),
        .PCsrc(PCsrc),
        .immediate(immediate),
        .PC(PC)
    );
    initial begin
        CLK = 0;
        forever #5 CLK = ~CLK;
    end
    initial begin
        $dumpfile("pc_tb.vcd");
        $dumpvars(0, pc_tb);
    end
    initial begin
        reset = 1;
        PCsrc = 0;
        immediate = 8'h00;

        #10 reset = 0;
        // Test 1: +1
        #10;
        // Test 2: +1
        #10;
        // Test 3: Load
        PCsrc = 1;
        immediate = 8'h10;
        #10;
        // Test 4: +1
        PCsrc = 0;
        #10;
        // Test 5: Load
        PCsrc = 1;
        immediate = 8'h20;
        #10;
        // Test 6: +1
        PCsrc = 0;
        #10;
        // Test 7: Load
        PCsrc = 1;
        immediate = 8'h30;
        #10;
        // Test 8: +1
        PCsrc = 0;
        #10;

        //reset
        reset = 1;
        #10;
        $finish;
    end

    initial begin
        $monitor("At time %t, PC = %d, reset = %b, PCsrc = %b, immediate = %d", $time, PC, reset, PCsrc, immediate);
    end

endmodule

pc_tb.vcd
$date
	Mon Feb 24 00:18:59 2025
$end
$version
	Icarus Verilog
$end
$timescale
	1ps
$end
$scope module pc_tb $end
$var wire 8 ! PC [7:0] $end
$var reg 1 " CLK $end
$var reg 1 # PCsrc $end
$var reg 8 $ immediate [7:0] $end
$var reg 1 % reset $end
$scope module uut $end
$var wire 1 " CLK $end
$var wire 1 # PCsrc $end
$var wire 8 & immediate [7:0] $end
$var wire 1 % reset $end
$var reg 8 ' PC [7:0] $end
$upscope $end
$upscope $end
$enddefinitions $end
$comment Show the parameter values. $end
$dumpall
$end
#0
$dumpvars
b0 '
b0 &
1%
b0 $
0#
0"
b0 !
$end
#5000
1"
#10000
0"
0%
#15000
b1 !
b1 '
1"
#20000
0"
#25000
b10 !
b10 '
1"
#30000
0"
b10000 $
b10000 &
1#
#35000
b10000 !
b10000 '
1"
#40000
0"
0#
#45000
b10001 !
b10001 '
1"
#50000
0"
b100000 $
b100000 &
1#
#55000
b100000 !
b100000 '
1"
#60000
0"
0#
#65000
b100001 !
b100001 '
1"
#70000
0"
b110000 $
b110000 &
1#
#75000
b110000 !
b110000 '
1"
#80000
0"
0#
#85000
b110001 !
b110001 '
1"
#90000
b0 !
b0 '
0"
1%
